{
  "iphones": [
    {
      "id": 1,
      "model": "iPhone 14",
      "image": "/images/iphone13.jpg",
      "isNew": true,
      "price": "16,900.00",
      "fullName": "[B] Apple iPhone 14"
    },
    {
      "id": 2,
      "model": "iPhone 14 Plus",
      "image": "/images/iphone14plus.jpg",
      "isNew": false,
      "price": "19,900.00",
      "fullName": "[B] Apple iPhone 14 Plus"
    },
    {
      "id": 3,
      "model": "iPhone 14 Pro",
      "image": "/images/iphone14pro.jpg",
      "isNew": true,
      "price": "24,900.00",
      "fullName": "[B] Apple iPhone 14 Pro"
    },
    {
      "id": 4,
      "model": "iPhone 14 Pro Max",
      "image": "/images/iphone14promax.jpg",
      "isNew": false,
      "price": "28,900.00",
      "fullName": "[B] Apple iPhone 14 Pro Max"
    },
    {
      "id": 5,
      "model": "iPhone 13",
      "image": "/images/iphone13.jpg",
      "isNew": false,
      "price": "14,900.00",
      "fullName": "[B] Apple iPhone 13"
    },
    {
      "id": 6,
      "model": "iPhone 13 Pro",
      "image": "/images/iphone13pro.jpg",
      "isNew": false,
      "price": "19,900.00",
      "fullName": "[B] Apple iPhone 13 Pro"
    }
  ]
}
